pglast/__init__.py
pglast/__main__.py
pglast/ast.py
pglast/ast.pyx
pglast/error.py
pglast/keywords.py
pglast/parser.c
pglast/parser.cpython-314t-x86_64-linux-gnu.so
pglast/parser.pyx
pglast/stream.py
pglast/structs.pxd
pglast/visitors.py
pglast/enums/__init__.py
pglast/enums/lockdefs.py
pglast/enums/lockoptions.py
pglast/enums/nodes.py
pglast/enums/parsenodes.py
pglast/enums/pg_am.py
pglast/enums/pg_attribute.py
pglast/enums/pg_class.py
pglast/enums/pg_trigger.py
pglast/enums/primnodes.py
pglast/enums/xml.py
pglast/printers/__init__.py
pglast/printers/ddl.py
pglast/printers/dml.py
pglast/printers/sfuncs.py
pglast-7.11.dist-info/METADATA
pglast-7.11.dist-info/WHEEL
pglast-7.11.dist-info/entry_points.txt
pglast-7.11.dist-info/top_level.txt
pglast-7.11.dist-info/RECORD
