Metadata-Version: 2.4
Name: pglast
Version: 7.11
Summary: PostgreSQL Languages AST and statements prettifier
Author-email: Lele Gaifax <lele@metapensiero.it>
License-Expression: GPL-3.0-or-later
Project-URL: Changelog, https://github.com/lelit/pglast/blob/v7/CHANGES.rst
Project-URL: Source, https://github.com/lelit/pglast
Keywords: postgresql,parser,sql,prettifier
Classifier: Development Status :: 5 - Production/Stable
Classifier: Intended Audience :: Developers
Classifier: Programming Language :: Python
Classifier: Programming Language :: Python :: 3
Classifier: Programming Language :: Python :: 3 :: Only
Classifier: Programming Language :: Python :: 3.9
Classifier: Programming Language :: Python :: 3.10
Classifier: Programming Language :: Python :: 3.11
Classifier: Programming Language :: Python :: 3.12
Classifier: Programming Language :: Python :: 3.13
Classifier: Programming Language :: Python :: 3.14
Classifier: Programming Language :: SQL
Classifier: Topic :: Database
Classifier: Topic :: Utilities
Provides-Extra: dev
Requires-Dist: bump-my-version==1.2.5; extra == "dev"
Requires-Dist: cython==3.2.3; extra == "dev"
Requires-Dist: pycparser==2.23; extra == "dev"
Requires-Dist: readme-renderer==44.0; extra == "dev"
Requires-Dist: setuptools==80.9.0; extra == "dev"
Requires-Dist: sphinx==9.0.4; extra == "dev"
Requires-Dist: twine==6.2.0; extra == "dev"
Provides-Extra: test
Requires-Dist: coverage==7.13.0; extra == "test"
Requires-Dist: pytest-cov==7.0.0; extra == "test"
Requires-Dist: pytest==9.0.2; extra == "test"
